chemsource/__init__.py
chemsource/chemsource.py
chemsource/classifier.py
chemsource/config.py
chemsource/exceptions.py
chemsource/retriever.py
chemsource-1.1.17.dist-info/licenses/LICENSE
chemsource-1.1.17.dist-info/METADATA
chemsource-1.1.17.dist-info/WHEEL
chemsource-1.1.17.dist-info/top_level.txt
chemsource-1.1.17.dist-info/RECORD
