Metadata-Version: 2.4
Name: chemsource
Version: 1.1.17
Summary: Tool to classify novel drugs and other health-related chemicals by origin
Author-email: Prajit Rajkumar <prajkumar@ucsd.edu>
Project-URL: Homepage, https://github.com/prajitrr/chemsource
Project-URL: Documentation, https://chemsource.readthedocs.io/
Project-URL: Repository, https://github.com/prajitrr/chemsource.git
Project-URL: Issues, https://github.com/prajitrr/chemsource/issues
Classifier: Programming Language :: Python :: 3
Classifier: License :: OSI Approved :: MIT License
Classifier: Operating System :: OS Independent
Requires-Python: >=3.8
License-File: LICENSE
Requires-Dist: lxml>=4.9.4
Requires-Dist: openai>=1.23.2
Requires-Dist: pyspellchecker>=0.8.1
Requires-Dist: requests<3,>=2.0.0
Requires-Dist: wikipedia>=1.4.0
Dynamic: license-file
